odoo/addons/currency_rate_update_VN_VCB/README.rst
odoo/addons/currency_rate_update_VN_VCB/__init__.py
odoo/addons/currency_rate_update_VN_VCB/__manifest__.py
odoo/addons/currency_rate_update_VN_VCB/models/__init__.py
odoo/addons/currency_rate_update_VN_VCB/models/currency_rate_update.py
odoo/addons/currency_rate_update_VN_VCB/services/__init__.py
odoo/addons/currency_rate_update_VN_VCB/services/update_service_VN_VCB.py
odoo/addons/currency_rate_update_VN_VCB/static/description/icon.png
odoo/addons/currency_rate_update_VN_VCB/tests/__init__.py
odoo/addons/currency_rate_update_VN_VCB/tests/test_currency_rate_update_vn_vcb.py
odoo11_addon_currency_rate_update_VN_VCB-11.0.1.0.0.99.dev5.dist-info/METADATA
odoo11_addon_currency_rate_update_VN_VCB-11.0.1.0.0.99.dev5.dist-info/RECORD
odoo11_addon_currency_rate_update_VN_VCB-11.0.1.0.0.99.dev5.dist-info/WHEEL
odoo11_addon_currency_rate_update_VN_VCB-11.0.1.0.0.99.dev5.dist-info/top_level.txt
